dea/__init__.py
dea/dea.py
ezdea-0.0.1.dist-info/LICENSE
ezdea-0.0.1.dist-info/METADATA
ezdea-0.0.1.dist-info/WHEEL
ezdea-0.0.1.dist-info/top_level.txt
ezdea-0.0.1.dist-info/RECORD
