Metadata-Version: 2.1
Name: ezdea
Version: 0.0.1
Summary: DEA - python interface
Home-page: https://github.com/jotavemonte/ezdea
Author: João Victor Monte R Tavares
Author-email: jotavmeonte@gmail.com
License: UNKNOWN
Platform: UNKNOWN
Classifier: Programming Language :: Python :: 3
Classifier: License :: OSI Approved :: MIT License
Classifier: Operating System :: OS Independent
